{"nm":"polar bear","ddd":0,"h":250,"w":250,"meta":{"g":"@lottiefiles/toolkit-js 0.33.2"},"layers":[{"ty":4,"nm":"Shape Layer 1","sr":1,"st":0,"op":300.00001221925,"ip":0,"hd":false,"ddd":0,"bm":0,"hasMask":false,"ao":0,"ks":{"a":{"a":0,"k":[-338.131,-320.165,0],"ix":1},"s":{"a":1,"k":[{"o":{"x":0.333,"y":0},"i":{"x":0.667,"y":1},"s":[23.15,23.15,100],"t":0},{"o":{"x":0.333,"y":0},"i":{"x":0.667,"y":1},"s":[3.47,3.47,100],"t":15},{"o":{"x":0.333,"y":0},"i":{"x":0.667,"y":1},"s":[3.47,3.47,100],"t":22},{"o":{"x":0.333,"y":0},"i":{"x":0.667,"y":1},"s":[29.63,29.63,100],"t":37},{"o":{"x":0.333,"y":0},"i":{"x":0.667,"y":1},"s":[29.63,29.63,100],"t":45},{"o":{"x":0.333,"y":0},"i":{"x":0.667,"y":1},"s":[11.58,11.58,100],"t":57},{"o":{"x":0.333,"y":0},"i":{"x":0.667,"y":1},"s":[11.58,11.58,100],"t":69},{"o":{"x":0.333,"y":0},"i":{"x":0.667,"y":1},"s":[29.63,29.63,100],"t":87},{"o":{"x":0.333,"y":0},"i":{"x":0.667,"y":1},"s":[29.63,29.63,100],"t":96},{"o":{"x":0.333,"y":0},"i":{"x":0.667,"y":1},"s":[23.15,23.15,100],"t":108},{"o":{"x":0.333,"y":0},"i":{"x":0.667,"y":1},"s":[23.15,23.15,100],"t":119},{"s":[23.15,23.15,100],"t":137.000005580124}],"ix":6},"sk":{"a":0,"k":0},"p":{"a":1,"k":[{"o":{"x":0.333,"y":0},"i":{"x":0.667,"y":1},"s":[116.64,176.35,0],"t":0},{"o":{"x":0.167,"y":0.167},"i":{"x":0.833,"y":0.833},"s":[51.94,99.5,0],"t":15},{"o":{"x":0.333,"y":0},"i":{"x":0.667,"y":1},"s":[51.94,99.5,0],"t":22},{"o":{"x":0.167,"y":0.167},"i":{"x":0.833,"y":0.833},"s":[190.36,86.54,0],"t":37},{"o":{"x":0.333,"y":0},"i":{"x":0.667,"y":1},"s":[190.36,86.54,0],"t":45},{"o":{"x":0.167,"y":0.167},"i":{"x":0.833,"y":0.833},"s":[129.71,74.5,0],"t":57},{"o":{"x":0.333,"y":0},"i":{"x":0.667,"y":1},"s":[129.71,74.5,0],"t":69},{"o":{"x":0.167,"y":0.167},"i":{"x":0.833,"y":0.833},"s":[50.09,218.02,0],"t":87},{"o":{"x":0.333,"y":0},"i":{"x":0.667,"y":1},"s":[50.09,218.02,0],"t":96},{"o":{"x":0.167,"y":0.167},"i":{"x":0.833,"y":0.833},"s":[208.42,219.87,0],"t":108},{"o":{"x":0.333,"y":0},"i":{"x":0.667,"y":1},"s":[208.42,219.87,0],"t":119},{"s":[116.64,176.35,0],"t":137.000005580124}],"ix":2},"r":{"a":1,"k":[{"o":{"x":0.333,"y":0},"i":{"x":0.667,"y":1},"s":[0],"t":0},{"s":[2520],"t":137.000005580124}],"ix":10},"sa":{"a":0,"k":0},"o":{"a":0,"k":69,"ix":11}},"ef":[],"shapes":[{"ty":"gr","bm":0,"hd":false,"mn":"ADBE Vector Group","nm":"Polystar 1","ix":1,"cix":2,"np":3,"it":[{"ty":"sr","bm":0,"hd":false,"mn":"ADBE Vector Shape - Star","nm":"Polystar Path 1","ix":1,"d":1,"ir":{"a":0,"k":11.632,"ix":6},"is":{"a":0,"k":0,"ix":8},"pt":{"a":0,"k":5,"ix":3},"p":{"a":0,"k":[0,0],"ix":4},"or":{"a":0,"k":23.264,"ix":7},"os":{"a":0,"k":0,"ix":9},"r":{"a":0,"k":0,"ix":5},"sy":1},{"ty":"fl","bm":0,"hd":false,"mn":"ADBE Vector Graphic - Fill","nm":"Fill 1","c":{"a":0,"k":[0.8549,0.6627,0.149],"ix":4},"r":1,"o":{"a":0,"k":100,"ix":5}},{"ty":"tr","a":{"a":0,"k":[0,0],"ix":1},"s":{"a":0,"k":[100,100],"ix":3},"sk":{"a":0,"k":0,"ix":4},"p":{"a":0,"k":[-338.131,-317.944],"ix":2},"r":{"a":0,"k":0,"ix":6},"sa":{"a":0,"k":0,"ix":5},"o":{"a":0,"k":100,"ix":7}}]}],"ind":1},{"ty":4,"nm":"nose Outlines","sr":1,"st":0,"op":300.00001221925,"ip":0,"hd":false,"ddd":0,"bm":0,"hasMask":false,"ao":0,"ks":{"a":{"a":0,"k":[12.25,12.25,0],"ix":1},"s":{"a":0,"k":[103.24,103.24,100],"ix":6},"sk":{"a":0,"k":0},"p":{"a":1,"k":[{"o":{"x":0.333,"y":0},"i":{"x":0.667,"y":1},"s":[116.74,177.31,0],"t":0},{"o":{"x":0.167,"y":0.167},"i":{"x":0.833,"y":0.833},"s":[97.06,163.89,0],"t":15},{"o":{"x":0.333,"y":0},"i":{"x":0.667,"y":1},"s":[97.06,163.89,0],"t":22},{"o":{"x":0.333,"y":0},"i":{"x":0.667,"y":1},"s":[143.59,163.65,0],"t":37},{"o":{"x":0.333,"y":0},"i":{"x":0.667,"y":1},"s":[143.59,163.65,0],"t":45},{"o":{"x":0.333,"y":0},"i":{"x":0.667,"y":1},"s":[116.97,141.66,0],"t":57},{"o":{"x":0.333,"y":0},"i":{"x":0.667,"y":1},"s":[116.97,137.73,0],"t":61},{"o":{"x":0.333,"y":0},"i":{"x":0.667,"y":1},"s":[116.97,141.66,0],"t":65},{"o":{"x":0.333,"y":0},"i":{"x":0.667,"y":1},"s":[116.97,141.66,0],"t":69},{"o":{"x":0.167,"y":0.167},"i":{"x":0.833,"y":0.833},"s":[94.98,178.35,0],"t":87},{"o":{"x":0.333,"y":0},"i":{"x":0.667,"y":1},"s":[94.98,178.35,0],"t":96},{"o":{"x":0.167,"y":0.167},"i":{"x":0.833,"y":0.833},"s":[139.43,178.12,0],"t":108},{"o":{"x":0.333,"y":0},"i":{"x":0.667,"y":1},"s":[139.43,178.12,0],"t":119},{"s":[116.74,177.31,0],"t":137.000005580124}],"ix":2},"r":{"a":0,"k":0,"ix":10},"sa":{"a":0,"k":0},"o":{"a":0,"k":100,"ix":11}},"ef":[],"shapes":[{"ty":"gr","bm":0,"hd":false,"mn":"ADBE Vector Group","nm":"Group 1","ix":1,"cix":2,"np":2,"it":[{"ty":"sh","bm":0,"hd":false,"mn":"ADBE Vector Shape - Group","nm":"Path 1","ix":1,"d":1,"ks":{"a":0,"k":{"c":true,"i":[[0,-1.104],[1.104,0],[0,1.104],[-1.104,0]],"o":[[0,1.104],[-1.104,0],[0,-1.104],[1.104,0]],"v":[[2,0],[0,2],[-2,0],[0,-2]]},"ix":2}},{"ty":"fl","bm":0,"hd":false,"mn":"ADBE Vector Graphic - Fill","nm":"Fill 1","c":{"a":0,"k":[1,1,1],"ix":4},"r":1,"o":{"a":0,"k":100,"ix":5}},{"ty":"tr","a":{"a":0,"k":[0,0],"ix":1},"s":{"a":0,"k":[100,100],"ix":3},"sk":{"a":0,"k":0,"ix":4},"p":{"a":0,"k":[6.75,6.75],"ix":2},"r":{"a":0,"k":0,"ix":6},"sa":{"a":0,"k":0,"ix":5},"o":{"a":0,"k":100,"ix":7}}]},{"ty":"gr","bm":0,"hd":false,"mn":"ADBE Vector Group","nm":"Group 2","ix":2,"cix":2,"np":2,"it":[{"ty":"sh","bm":0,"hd":false,"mn":"ADBE Vector Shape - Group","nm":"Path 1","ix":1,"d":1,"ks":{"a":0,"k":{"c":true,"i":[[0,-6.627],[6.627,0],[0,6.627],[-6.627,0]],"o":[[0,6.627],[-6.627,0],[0,-6.627],[6.627,0]],"v":[[12,0],[0,12],[-12,0],[0,-12]]},"ix":2}},{"ty":"fl","bm":0,"hd":false,"mn":"ADBE Vector Graphic - Fill","nm":"Fill 1","c":{"a":0,"k":[0,0,0],"ix":4},"r":1,"o":{"a":0,"k":100,"ix":5}},{"ty":"tr","a":{"a":0,"k":[0,0],"ix":1},"s":{"a":0,"k":[100,100],"ix":3},"sk":{"a":0,"k":0,"ix":4},"p":{"a":0,"k":[12.25,12.25],"ix":2},"r":{"a":0,"k":0,"ix":6},"sa":{"a":0,"k":0,"ix":5},"o":{"a":0,"k":100,"ix":7}}]}],"ind":2},{"ty":4,"nm":"left eye Outlines","sr":1,"st":0,"op":300.00001221925,"ip":0,"hd":false,"ddd":0,"bm":0,"hasMask":false,"ao":0,"ks":{"a":{"a":0,"k":[4.25,4.25,0],"ix":1},"s":{"a":1,"k":[{"o":{"x":0.167,"y":0},"i":{"x":0.667,"y":1},"s":[103.24,103.24,100],"t":0},{"o":{"x":0.333,"y":0},"i":{"x":0.667,"y":1},"s":[103.24,103.24,100],"t":15},{"o":{"x":0.333,"y":0},"i":{"x":0.667,"y":1},"s":[103.24,103.24,100],"t":22},{"o":{"x":0.333,"y":0},"i":{"x":0.667,"y":1},"s":[72.92,72.92,100],"t":37},{"o":{"x":0.333,"y":0},"i":{"x":0.667,"y":1},"s":[72.92,72.92,100],"t":45},{"o":{"x":0.333,"y":0},"i":{"x":0.667,"y":1},"s":[78.47,78.47,100],"t":57},{"o":{"x":0.333,"y":0},"i":{"x":0.667,"y":1},"s":[78.47,78.47,100],"t":69},{"o":{"x":0.333,"y":0},"i":{"x":0.667,"y":1},"s":[90.51,90.51,100],"t":87},{"o":{"x":0.333,"y":0},"i":{"x":0.833,"y":1},"s":[90.51,90.51,100],"t":96},{"o":{"x":0.167,"y":0},"i":{"x":0.833,"y":1},"s":[69.91,69.91,100],"t":108},{"o":{"x":0.167,"y":0},"i":{"x":0.833,"y":1},"s":[69.91,69.91,100],"t":119},{"s":[103.24,103.24,100],"t":137.000005580124}],"ix":6},"sk":{"a":0,"k":0},"p":{"a":1,"k":[{"o":{"x":0.333,"y":0},"i":{"x":0.667,"y":1},"s":[129.13,150.47,0],"t":0},{"o":{"x":0.167,"y":0.167},"i":{"x":0.833,"y":0.833},"s":[115.36,143.29,0],"t":15},{"o":{"x":0.333,"y":0},"i":{"x":0.667,"y":1},"s":[115.36,143.29,0],"t":22},{"o":{"x":0.333,"y":0},"i":{"x":0.667,"y":1},"s":[151.41,143.41,0],"t":37},{"o":{"x":0.333,"y":0},"i":{"x":0.667,"y":1},"s":[151.41,143.41,0],"t":45},{"o":{"x":0.167,"y":0.167},"i":{"x":0.833,"y":0.833},"s":[128.73,124.2,0],"t":57},{"o":{"x":0.333,"y":0},"i":{"x":0.667,"y":1},"s":[128.73,124.2,0],"t":69},{"o":{"x":0.333,"y":0},"i":{"x":0.667,"y":1},"s":[111.77,156.55,0],"t":87},{"o":{"x":0.333,"y":0},"i":{"x":0.667,"y":1},"s":[111.77,156.55,0],"t":96},{"o":{"x":0.333,"y":0},"i":{"x":0.667,"y":1},"s":[146.61,157.47,0],"t":108},{"o":{"x":0.333,"y":0},"i":{"x":0.667,"y":1},"s":[146.61,157.47,0],"t":119},{"s":[129.13,150.47,0],"t":137.000005580124}],"ix":2},"r":{"a":0,"k":0,"ix":10},"sa":{"a":0,"k":0},"o":{"a":0,"k":100,"ix":11}},"ef":[],"shapes":[{"ty":"gr","bm":0,"hd":false,"mn":"ADBE Vector Group","nm":"Group 1","ix":1,"cix":2,"np":2,"it":[{"ty":"sh","bm":0,"hd":false,"mn":"ADBE Vector Shape - Group","nm":"Path 1","ix":1,"d":1,"ks":{"a":0,"k":{"c":true,"i":[[0,-2.209],[2.209,0],[0,2.209],[-2.209,0]],"o":[[0,2.209],[-2.209,0],[0,-2.209],[2.209,0]],"v":[[4,0],[0,4],[-4,0],[0,-4]]},"ix":2}},{"ty":"fl","bm":0,"hd":false,"mn":"ADBE Vector Graphic - Fill","nm":"Fill 1","c":{"a":0,"k":[0,0,0],"ix":4},"r":1,"o":{"a":0,"k":100,"ix":5}},{"ty":"tr","a":{"a":0,"k":[0,0],"ix":1},"s":{"a":0,"k":[100,100],"ix":3},"sk":{"a":0,"k":0,"ix":4},"p":{"a":0,"k":[4.25,4.25],"ix":2},"r":{"a":0,"k":0,"ix":6},"sa":{"a":0,"k":0,"ix":5},"o":{"a":0,"k":100,"ix":7}}]}],"ind":3},{"ty":4,"nm":"right eye Outlines","sr":1,"st":0,"op":300.00001221925,"ip":0,"hd":false,"ddd":0,"bm":0,"hasMask":false,"ao":0,"ks":{"a":{"a":0,"k":[4.25,4.25,0],"ix":1},"s":{"a":1,"k":[{"o":{"x":0.333,"y":0},"i":{"x":0.667,"y":1},"s":[103.24,103.24,100],"t":0},{"o":{"x":0.333,"y":0},"i":{"x":0.667,"y":1},"s":[70.14,70.14,100],"t":15},{"o":{"x":0.333,"y":0},"i":{"x":0.667,"y":1},"s":[70.14,70.14,100],"t":22},{"o":{"x":0.333,"y":0},"i":{"x":0.667,"y":1},"s":[84.03,84.03,100],"t":37},{"o":{"x":0.333,"y":0},"i":{"x":0.667,"y":1},"s":[84.03,84.03,100],"t":45},{"o":{"x":0.333,"y":0},"i":{"x":0.667,"y":1},"s":[84.03,84.03,100],"t":69},{"o":{"x":0.333,"y":0},"i":{"x":0.667,"y":1},"s":[69.91,69.91,100],"t":87},{"o":{"x":0.333,"y":0},"i":{"x":0.833,"y":1},"s":[69.91,69.91,100],"t":96},{"o":{"x":0.167,"y":0},"i":{"x":0.833,"y":1},"s":[93.52,93.52,100],"t":108},{"o":{"x":0.167,"y":0},"i":{"x":0.833,"y":1},"s":[93.52,93.52,100],"t":119},{"s":[103.24,103.24,100],"t":137.000005580124}],"ix":6},"sk":{"a":0,"k":0},"p":{"a":1,"k":[{"o":{"x":0.333,"y":0},"i":{"x":0.667,"y":1},"s":[103.32,150.47,0],"t":0},{"o":{"x":0.167,"y":0.167},"i":{"x":0.833,"y":0.833},"s":[88.74,143.64,0],"t":15},{"o":{"x":0.333,"y":0},"i":{"x":0.667,"y":1},"s":[88.74,143.64,0],"t":22},{"o":{"x":0.333,"y":0},"i":{"x":0.667,"y":1},"s":[125.02,143.47,0],"t":37},{"o":{"x":0.333,"y":0},"i":{"x":0.667,"y":1},"s":[125.02,143.47,0],"t":45},{"o":{"x":0.167,"y":0.167},"i":{"x":0.833,"y":0.833},"s":[102.57,124.2,0],"t":57},{"o":{"x":0.333,"y":0},"i":{"x":0.667,"y":1},"s":[102.57,124.2,0],"t":69},{"o":{"x":0.333,"y":0},"i":{"x":0.667,"y":1},"s":[84.98,156.84,0],"t":87},{"o":{"x":0.333,"y":0},"i":{"x":0.667,"y":1},"s":[84.98,156.84,0],"t":96},{"o":{"x":0.333,"y":0},"i":{"x":0.667,"y":1},"s":[119.81,157.41,0],"t":108},{"o":{"x":0.333,"y":0},"i":{"x":0.667,"y":1},"s":[119.81,157.41,0],"t":119},{"s":[103.32,150.47,0],"t":137.000005580124}],"ix":2},"r":{"a":0,"k":0,"ix":10},"sa":{"a":0,"k":0},"o":{"a":0,"k":100,"ix":11}},"ef":[],"shapes":[{"ty":"gr","bm":0,"hd":false,"mn":"ADBE Vector Group","nm":"Group 1","ix":1,"cix":2,"np":2,"it":[{"ty":"sh","bm":0,"hd":false,"mn":"ADBE Vector Shape - Group","nm":"Path 1","ix":1,"d":1,"ks":{"a":0,"k":{"c":true,"i":[[0,-2.209],[2.209,0],[0,2.209],[-2.209,0]],"o":[[0,2.209],[-2.209,0],[0,-2.209],[2.209,0]],"v":[[4,0],[0,4],[-4,0],[0,-4]]},"ix":2}},{"ty":"fl","bm":0,"hd":false,"mn":"ADBE Vector Graphic - Fill","nm":"Fill 1","c":{"a":0,"k":[0,0,0],"ix":4},"r":1,"o":{"a":0,"k":100,"ix":5}},{"ty":"tr","a":{"a":0,"k":[0,0],"ix":1},"s":{"a":0,"k":[100,100],"ix":3},"sk":{"a":0,"k":0,"ix":4},"p":{"a":0,"k":[4.25,4.25],"ix":2},"r":{"a":0,"k":0,"ix":6},"sa":{"a":0,"k":0,"ix":5},"o":{"a":0,"k":100,"ix":7}}]}],"ind":4},{"ty":4,"nm":"ear left Outlines","sr":1,"st":0,"op":300.00001221925,"ip":0,"hd":false,"ddd":0,"bm":0,"hasMask":false,"ao":0,"ks":{"a":{"a":0,"k":[17.25,17.25,0],"ix":1},"s":{"a":0,"k":[103.24,103.24,100],"ix":6},"sk":{"a":0,"k":0},"p":{"a":1,"k":[{"o":{"x":0.333,"y":0},"i":{"x":0.667,"y":1},"s":[175.59,143.24,0],"t":0},{"o":{"x":0.167,"y":0.167},"i":{"x":0.833,"y":0.833},"s":[177.09,147.87,0],"t":15},{"o":{"x":0.167,"y":0},"i":{"x":0.667,"y":1},"s":[177.09,147.87,0],"t":22},{"o":{"x":0.167,"y":0.167},"i":{"x":0.833,"y":0.833},"s":[168.76,147.53,0],"t":37},{"o":{"x":0.167,"y":0},"i":{"x":0.667,"y":1},"s":[168.76,147.53,0],"t":45},{"o":{"x":0.167,"y":0.167},"i":{"x":0.833,"y":0.833},"s":[169.11,151.69,0],"t":57},{"o":{"x":0.167,"y":0},"i":{"x":0.667,"y":1},"s":[169.11,151.69,0],"t":69},{"o":{"x":0.167,"y":0.167},"i":{"x":0.833,"y":0.833},"s":[173.5,161.07,0],"t":87},{"o":{"x":0.167,"y":0},"i":{"x":0.667,"y":1},"s":[173.5,161.07,0],"t":96},{"o":{"x":0.167,"y":0.167},"i":{"x":0.833,"y":0.833},"s":[165.64,161.53,0],"t":108},{"o":{"x":0.167,"y":0},"i":{"x":0.667,"y":1},"s":[165.64,161.53,0],"t":119},{"s":[175.59,143.24,0],"t":137.000005580124}],"ix":2},"r":{"a":0,"k":0,"ix":10},"sa":{"a":0,"k":0},"o":{"a":0,"k":100,"ix":11}},"ef":[],"shapes":[{"ty":"gr","bm":0,"hd":false,"mn":"ADBE Vector Group","nm":"Group 1","ix":1,"cix":2,"np":2,"it":[{"ty":"sh","bm":0,"hd":false,"mn":"ADBE Vector Shape - Group","nm":"Path 1","ix":1,"d":1,"ks":{"a":0,"k":{"c":true,"i":[[0,-9.389],[9.389,0],[0,9.389],[-9.389,0]],"o":[[0,9.389],[-9.389,0],[0,-9.389],[9.389,0]],"v":[[17,0],[0,17],[-17,0],[0,-17]]},"ix":2}},{"ty":"fl","bm":0,"hd":false,"mn":"ADBE Vector Graphic - Fill","nm":"Fill 1","c":{"a":0,"k":[1,1,1],"ix":4},"r":1,"o":{"a":0,"k":100,"ix":5}},{"ty":"tr","a":{"a":0,"k":[0,0],"ix":1},"s":{"a":0,"k":[100,100],"ix":3},"sk":{"a":0,"k":0,"ix":4},"p":{"a":0,"k":[17.25,17.25],"ix":2},"r":{"a":0,"k":0,"ix":6},"sa":{"a":0,"k":0,"ix":5},"o":{"a":0,"k":100,"ix":7}}]}],"ind":5},{"ty":4,"nm":"ear right Outlines","sr":1,"st":0,"op":300.00001221925,"ip":0,"hd":false,"ddd":0,"bm":0,"hasMask":false,"ao":0,"ks":{"a":{"a":0,"k":[17.25,17.25,0],"ix":1},"s":{"a":0,"k":[103.24,103.24,100],"ix":6},"sk":{"a":0,"k":0},"p":{"a":1,"k":[{"o":{"x":0.333,"y":0},"i":{"x":0.667,"y":1},"s":[56.86,143.24,0],"t":0},{"o":{"x":0.167,"y":0.167},"i":{"x":0.833,"y":0.833},"s":[62.42,147.06,0],"t":15},{"o":{"x":0.167,"y":0},"i":{"x":0.667,"y":1},"s":[62.42,147.06,0],"t":22},{"o":{"x":0.167,"y":0.167},"i":{"x":0.833,"y":0.833},"s":[54.08,147.87,0],"t":37},{"o":{"x":0.167,"y":0},"i":{"x":0.667,"y":1},"s":[54.08,147.87,0],"t":45},{"o":{"x":0.167,"y":0.167},"i":{"x":0.833,"y":0.833},"s":[62.88,152.15,0],"t":57},{"o":{"x":0.167,"y":0},"i":{"x":0.667,"y":1},"s":[62.88,152.15,0],"t":69},{"o":{"x":0.167,"y":0.167},"i":{"x":0.833,"y":0.833},"s":[63.11,161.53,0],"t":87},{"o":{"x":0.167,"y":0},"i":{"x":0.667,"y":1},"s":[63.11,161.53,0],"t":96},{"o":{"x":0.167,"y":0.167},"i":{"x":0.833,"y":0.833},"s":[56.4,161.41,0],"t":108},{"o":{"x":0.167,"y":0},"i":{"x":0.667,"y":1},"s":[56.4,161.41,0],"t":119},{"s":[56.86,143.24,0],"t":137.000005580124}],"ix":2},"r":{"a":0,"k":0,"ix":10},"sa":{"a":0,"k":0},"o":{"a":0,"k":100,"ix":11}},"ef":[],"shapes":[{"ty":"gr","bm":0,"hd":false,"mn":"ADBE Vector Group","nm":"Group 1","ix":1,"cix":2,"np":2,"it":[{"ty":"sh","bm":0,"hd":false,"mn":"ADBE Vector Shape - Group","nm":"Path 1","ix":1,"d":1,"ks":{"a":0,"k":{"c":true,"i":[[0,-9.389],[9.389,0],[0,9.389],[-9.389,0]],"o":[[0,9.389],[-9.389,0],[0,-9.389],[9.389,0]],"v":[[17,0],[0,17],[-17,0],[0,-17]]},"ix":2}},{"ty":"fl","bm":0,"hd":false,"mn":"ADBE Vector Graphic - Fill","nm":"Fill 1","c":{"a":0,"k":[1,1,1],"ix":4},"r":1,"o":{"a":0,"k":100,"ix":5}},{"ty":"tr","a":{"a":0,"k":[0,0],"ix":1},"s":{"a":0,"k":[100,100],"ix":3},"sk":{"a":0,"k":0,"ix":4},"p":{"a":0,"k":[17.25,17.25],"ix":2},"r":{"a":0,"k":0,"ix":6},"sa":{"a":0,"k":0,"ix":5},"o":{"a":0,"k":100,"ix":7}}]}],"ind":6},{"ty":4,"nm":"Layer 1 Outlines","sr":1,"st":0,"op":300.00001221925,"ip":0,"hd":false,"ddd":0,"bm":0,"hasMask":false,"ao":0,"ks":{"a":{"a":0,"k":[16.75,24.75,0],"ix":1},"s":{"a":0,"k":[103.24,103.24,100],"ix":6},"sk":{"a":0,"k":0},"p":{"a":1,"k":[{"o":{"x":0.333,"y":0},"i":{"x":0.667,"y":1},"s":[116.23,182.99,0],"t":0},{"o":{"x":0.167,"y":0.167},"i":{"x":0.833,"y":0.833},"s":[102.1,177.2,0],"t":15},{"o":{"x":0.333,"y":0},"i":{"x":0.667,"y":1},"s":[102.1,177.2,0],"t":22},{"o":{"x":0.167,"y":0.167},"i":{"x":0.833,"y":0.833},"s":[137.29,177.44,0],"t":37},{"o":{"x":0.333,"y":0},"i":{"x":0.667,"y":1},"s":[137.29,177.44,0],"t":45},{"o":{"x":0.333,"y":0},"i":{"x":0.667,"y":1},"s":[116.23,157.99,0],"t":57},{"o":{"x":0.333,"y":0},"i":{"x":0.667,"y":1},"s":[116.23,157.99,0],"t":69},{"o":{"x":0.167,"y":0},"i":{"x":0.667,"y":1},"s":[98.4,190.63,0],"t":87},{"o":{"x":0.167,"y":0},"i":{"x":0.667,"y":1},"s":[98.4,190.63,0],"t":96},{"o":{"x":0.167,"y":0},"i":{"x":0.667,"y":1},"s":[133.35,191.09,0],"t":108},{"o":{"x":0.167,"y":0},"i":{"x":0.667,"y":1},"s":[133.35,191.09,0],"t":119},{"s":[116.23,182.99,0],"t":137.000005580124}],"ix":2},"r":{"a":0,"k":0,"ix":10},"sa":{"a":0,"k":0},"o":{"a":0,"k":100,"ix":11}},"ef":[],"shapes":[{"ty":"gr","bm":0,"hd":false,"mn":"ADBE Vector Group","nm":"Group 1","ix":1,"cix":2,"np":3,"it":[{"ty":"sh","bm":0,"hd":false,"mn":"ADBE Vector Shape - Group","nm":"Path 1","ix":1,"d":1,"ks":{"a":0,"k":{"c":false,"i":[[0,0],[0,0]],"o":[[0,0],[0,0]],"v":[[13.25,39.25],[20.25,39.25]]},"ix":2}},{"ty":"st","bm":0,"hd":false,"mn":"ADBE Vector Graphic - Stroke","nm":"Stroke 1","lc":1,"lj":1,"ml":10,"o":{"a":0,"k":100,"ix":4},"w":{"a":0,"k":1,"ix":5},"c":{"a":0,"k":[0,0,0],"ix":3}},{"ty":"fl","bm":0,"hd":false,"mn":"ADBE Vector Graphic - Fill","nm":"Fill 1","c":{"a":0,"k":[0,0,0],"ix":4},"r":1,"o":{"a":0,"k":100,"ix":5}},{"ty":"tr","a":{"a":0,"k":[0,0],"ix":1},"s":{"a":0,"k":[100,100],"ix":3},"sk":{"a":0,"k":0,"ix":4},"p":{"a":0,"k":[0,0],"ix":2},"r":{"a":0,"k":0,"ix":6},"sa":{"a":0,"k":0,"ix":5},"o":{"a":0,"k":100,"ix":7}}]},{"ty":"gr","bm":0,"hd":false,"mn":"ADBE Vector Group","nm":"Group 2","ix":2,"cix":2,"np":2,"it":[{"ty":"sh","bm":0,"hd":false,"mn":"ADBE Vector Shape - Group","nm":"Path 1","ix":1,"d":1,"ks":{"a":0,"k":{"c":true,"i":[[9.112,0],[0,0],[0,9.112],[0,0],[-9.112,0],[0,-9.113],[0,0]],"o":[[0,0],[-9.112,0],[0,0],[0,-9.113],[9.112,0],[0,0],[0,9.112]],"v":[[0,24.5],[0,24.5],[-16.5,8],[-16.5,-8],[0,-24.5],[16.5,-8],[16.5,8]]},"ix":2}},{"ty":"fl","bm":0,"hd":false,"mn":"ADBE Vector Graphic - Fill","nm":"Fill 1","c":{"a":0,"k":[0.8784,0.9765,1],"ix":4},"r":1,"o":{"a":0,"k":100,"ix":5}},{"ty":"tr","a":{"a":0,"k":[0,0],"ix":1},"s":{"a":0,"k":[100,100],"ix":3},"sk":{"a":0,"k":0,"ix":4},"p":{"a":0,"k":[16.75,24.75],"ix":2},"r":{"a":0,"k":0,"ix":6},"sa":{"a":0,"k":0,"ix":5},"o":{"a":0,"k":100,"ix":7}}]}],"ind":7},{"ty":4,"nm":"Layer 8 Outlines","sr":1,"st":0,"op":300.00001221925,"ip":0,"hd":false,"ddd":0,"bm":0,"hasMask":false,"ao":0,"ks":{"a":{"a":0,"k":[58.75,66.75,0],"ix":1},"s":{"a":0,"k":[103.24,103.24,100],"ix":6},"sk":{"a":0,"k":0},"p":{"a":0,"k":[115.71,182.48,0],"ix":2},"r":{"a":0,"k":0,"ix":10},"sa":{"a":0,"k":0},"o":{"a":0,"k":100,"ix":11}},"ef":[],"shapes":[{"ty":"gr","bm":0,"hd":false,"mn":"ADBE Vector Group","nm":"Group 1","ix":1,"cix":2,"np":2,"it":[{"ty":"sh","bm":0,"hd":false,"mn":"ADBE Vector Shape - Group","nm":"Path 1","ix":1,"d":1,"ks":{"a":0,"k":{"c":true,"i":[[0,0],[0,0],[0,0],[-30.869,0],[0,0],[0,-30.217]],"o":[[0,0],[0,0],[0,-30.869],[0,0],[30.218,0],[0,0]],"v":[[58.5,66.5],[-58.5,66.5],[-58.5,-10.607],[-2.607,-66.5],[3.786,-66.5],[58.5,-11.786]]},"ix":2}},{"ty":"fl","bm":0,"hd":false,"mn":"ADBE Vector Graphic - Fill","nm":"Fill 1","c":{"a":0,"k":[1,1,1],"ix":4},"r":1,"o":{"a":0,"k":100,"ix":5}},{"ty":"tr","a":{"a":0,"k":[0,0],"ix":1},"s":{"a":0,"k":[100,100],"ix":3},"sk":{"a":0,"k":0,"ix":4},"p":{"a":0,"k":[58.75,66.75],"ix":2},"r":{"a":0,"k":0,"ix":6},"sa":{"a":0,"k":0,"ix":5},"o":{"a":0,"k":100,"ix":7}}]}],"ind":8},{"ty":1,"nm":"Medium Cyan Solid 1","sr":1,"st":0,"op":300.00001221925,"ip":0,"hd":false,"ddd":0,"bm":0,"hasMask":false,"ao":0,"ks":{"a":{"a":0,"k":[540,540,0],"ix":1},"s":{"a":0,"k":[23.15,23.15,100],"ix":6},"sk":{"a":0,"k":0},"p":{"a":0,"k":[125,125,0],"ix":2},"r":{"a":0,"k":0,"ix":10},"sa":{"a":0,"k":0},"o":{"a":0,"k":100,"ix":11}},"ef":[],"sc":"#a6ddeb","sh":1080,"sw":1080,"ind":9}],"v":"5.7.13","fr":29.9700012207031,"op":151.000006150356,"ip":0,"assets":[]}